nihtest/Command.py
nihtest/CompareArrays.py
nihtest/Configuration.py
nihtest/Directory.py
nihtest/Environment.py
nihtest/Features.py
nihtest/File.py
nihtest/Output.py
nihtest/Sandbox.py
nihtest/Suite.py
nihtest/Test.py
nihtest/TestCase.py
nihtest/Utility.py
nihtest/__init__.py
nihtest/__main__.py
nihtest-1.10.0.dist-info/licenses/LICENSE
nihtest-1.10.0.dist-info/METADATA
nihtest-1.10.0.dist-info/WHEEL
nihtest-1.10.0.dist-info/entry_points.txt
nihtest-1.10.0.dist-info/top_level.txt
nihtest-1.10.0.dist-info/RECORD
