Metadata-Version: 2.4
Name: nihtest
Version: 1.10.0
Summary: A testing tool for command line utilities.
Author-email: Dieter Baron <dillo@nih.at>, Thomas Klausner <wiz@gatalith.at>
License-Expression: BSD-3-Clause
Project-URL: Homepage, https://github.com/nih-at/nihtest
Project-URL: Bug Tracker, https://github.com/nih-at/nihtest/issues
Classifier: Programming Language :: Python :: 3
Classifier: Operating System :: OS Independent
Requires-Python: >=3.9
License-File: LICENSE
Requires-Dist: python-dateutil
Dynamic: license-file
